bendis_arm/__init__.py
bendis_arm/env.py
bendis_arm-0.9.dist-info/METADATA
bendis_arm-0.9.dist-info/WHEEL
bendis_arm-0.9.dist-info/top_level.txt
bendis_arm-0.9.dist-info/RECORD
