Metadata-Version: 2.2
Name: bendis_arm
Version: 0.9
Summary: A robotic arm environment for reinforcement learning
Home-page: https://huggingface.com/Gargaz
Author: Bendis
Author-email: gargazlucaaleaxndru@gmai.com
Classifier: Programming Language :: Python :: 3
Classifier: License :: OSI Approved :: MIT License
Classifier: Operating System :: OS Independent
Requires-Python: >=3.6
Requires-Dist: gym
Requires-Dist: pybullet
Requires-Dist: numpy
Requires-Dist: stable-baselines3
Requires-Dist: opencv-python
Dynamic: author
Dynamic: author-email
Dynamic: classifier
Dynamic: home-page
Dynamic: requires-dist
Dynamic: requires-python
Dynamic: summary
